scBalance/__init__.py
scBalance/scBalance_classifier.py
scBalance/scbalance_IO.py
scBalance/weightsampling.py
scBalance-1.2.0.dist-info/LICENSE
scBalance-1.2.0.dist-info/METADATA
scBalance-1.2.0.dist-info/WHEEL
scBalance-1.2.0.dist-info/top_level.txt
scBalance-1.2.0.dist-info/RECORD
