Metadata-Version: 2.1
Name: scBalance
Version: 1.2.0
Summary: scBalance, a neural network framework, provides a fast and reliable tools for scRNA-seq profile auto-annotation.
Home-page: https://github.com/yuqcheng/scBalance
Author: Yuqi Cheng
Author-email: yuc4009@med.cornell.edu
License: MIT Licence
Platform: UNKNOWN
Requires-Python: >=3.5.0
License-File: LICENSE
